plasmapy_sphinx/__init__.py
plasmapy_sphinx/utils.py
plasmapy_sphinx/autodoc/__init__.py
plasmapy_sphinx/autodoc/automodapi.py
plasmapy_sphinx/automodsumm/__init__.py
plasmapy_sphinx/automodsumm/core.py
plasmapy_sphinx/automodsumm/generate.py
plasmapy_sphinx/directives/__init__.py
plasmapy_sphinx/directives/confval.py
plasmapy_sphinx/directives/event.py
plasmapy_sphinx/ext/__init__.py
plasmapy_sphinx/ext/autodoc.py
plasmapy_sphinx/ext/automodsumm.py
plasmapy_sphinx/ext/css.py
plasmapy_sphinx/ext/directives.py
plasmapy_sphinx/theme/__init__.py
plasmapy_sphinx/theme/breadcrumbs.html
plasmapy_sphinx/theme/footer.html
plasmapy_sphinx/theme/layout.html
plasmapy_sphinx/theme/theme.conf
plasmapy_sphinx/theme/static/css/admonition_color_contrast.css
plasmapy_sphinx/theme/static/css/plasmapy.css
plasmapy_sphinx/theme/static/templates/automodsumm/base.rst
plasmapy_sphinx/theme/static/templates/automodsumm/class.rst
plasmapy_sphinx/theme/static/templates/automodsumm/module.rst
plasmapy_sphinx-2025.5.1.dist-info/licenses/LICENSE.md
plasmapy_sphinx-2025.5.1.dist-info/METADATA
plasmapy_sphinx-2025.5.1.dist-info/WHEEL
plasmapy_sphinx-2025.5.1.dist-info/entry_points.txt
plasmapy_sphinx-2025.5.1.dist-info/top_level.txt
plasmapy_sphinx-2025.5.1.dist-info/RECORD
