Metadata-Version: 2.4
Name: plasmapy_sphinx
Version: 2025.5.1
Summary: Sphinx extensions for the PlasmaPy Project
Maintainer-email: "Erik T. Everson" <eeverson@plasmapy.org>, "Nicholas A. Murphy" <namurphy@cfa.harvard.edu>
License: # BSD 2-Clause License
Project-URL: Chat, https://www.plasmapy.org/chat
Project-URL: Documentation, https://docs.plasmapy_sphinx.plasmapy.org
Project-URL: Issues, https://github.com/plasmapy/plasmapy_sphinx/issues
Project-URL: Source, https://github.com/plasmapy/plasmapy_sphinx
Project-URL: website, https://www.plasmapy.org
Keywords: plasmapy,sphinx,documentation
Classifier: Development Status :: 4 - Beta
Classifier: Intended Audience :: Science/Research
Classifier: License :: OSI Approved :: BSD License
Classifier: Operating System :: OS Independent
Classifier: Programming Language :: Python :: 3
Classifier: Programming Language :: Python :: 3.8
Classifier: Programming Language :: Python :: 3.8
Classifier: Programming Language :: Python :: 3.9
Classifier: Programming Language :: Python :: 3.10
Classifier: Programming Language :: Python :: 3.11
Classifier: Programming Language :: Python :: 3.12
Requires-Python: >=3.8
License-File: LICENSE.md
Requires-Dist: docutils
Requires-Dist: importlib_metadata; python_version < "3.8"
Requires-Dist: jinja2!=3.1
Requires-Dist: packaging
Requires-Dist: sphinx>=4.4
Requires-Dist: sphinx-gallery
Requires-Dist: sphinx_rtd_theme>=1.0.0
Provides-Extra: tests
Requires-Dist: codespell; extra == "tests"
Requires-Dist: dlint; extra == "tests"
Requires-Dist: flake8; extra == "tests"
Requires-Dist: flake8-absolute-import; extra == "tests"
Requires-Dist: flake8-implicit-str-concat; extra == "tests"
Requires-Dist: flake8-mutable; extra == "tests"
Requires-Dist: flake8-rst-docstrings; extra == "tests"
Requires-Dist: flake8-simplify; extra == "tests"
Requires-Dist: flake8-use-fstring; extra == "tests"
Requires-Dist: hypothesis; extra == "tests"
Requires-Dist: pre-commit; extra == "tests"
Requires-Dist: pydocstyle; extra == "tests"
Requires-Dist: pytest>=5.4.0; extra == "tests"
Requires-Dist: pytest-regressions; extra == "tests"
Requires-Dist: pytest-xdist; extra == "tests"
Requires-Dist: tox; extra == "tests"
Provides-Extra: docs
Requires-Dist: numpydoc; extra == "docs"
Requires-Dist: packaging; extra == "docs"
Requires-Dist: pillow; extra == "docs"
Requires-Dist: plasmapy>8.0; extra == "docs"
Requires-Dist: pygments>=2.11.0; extra == "docs"
Requires-Dist: sphinx-changelog; extra == "docs"
Requires-Dist: sphinx-copybutton; extra == "docs"
Requires-Dist: sphinx-hoverxref>=1.1.1; extra == "docs"
Requires-Dist: sphinx-issues>=3.0.1; extra == "docs"
Requires-Dist: sphinx-notfound-page>=0.8; extra == "docs"
Requires-Dist: sphinx-reredirects; extra == "docs"
Requires-Dist: sphinxcontrib-bibtex; extra == "docs"
Requires-Dist: towncrier>=19.2.0; extra == "docs"
Dynamic: license-file
